[{"gloss":"headache","instances":[{"bbox":[0,0,360,240],"fps":25,"frame_end":920,"frame_start":878,"instance_id":0,"signer_id":9,"source":"asl5200","split":"test","url":"https:\/\/www.youtube.com\/watch?v=SiBub8VD5wo","variation_id":0,"video_id":"26832"},{"bbox":[303,24,829,480],"fps":25,"frame_end":-1,"frame_start":1,"instance_id":1,"signer_id":60,"source":"signschool","split":"test","url":"https:\/\/signstock.blob.core.windows.net\/signschool\/videos\/db_uploads\/SignSchool%20Bad%20Headache-_dx7n545hbc.mp4","variation_id":0,"video_id":"26835"},{"bbox":[315,25,808,480],"fps":25,"frame_end":-1,"frame_start":1,"instance_id":2,"signer_id":60,"source":"signschool","split":"train","url":"https:\/\/signstock.blob.core.windows.net\/signschool\/videos\/db_uploads\/Signschool%20Headache-J1Y1SuISPL0.mp4","variation_id":0,"video_id":"26836"},{"bbox":[24,2,591,480],"fps":25,"frame_end":-1,"frame_start":1,"instance_id":3,"signer_id":21,"source":"asldeafined","split":"train","url":"https:\/\/media.asldeafined.com\/vocabulary\/1468580092.2901.mp4","variation_id":0,"video_id":"26837"},{"bbox":[29,20,302,240],"fps":25,"frame_end":-1,"frame_start":1,"instance_id":4,"signer_id":14,"source":"handspeak","split":"val","url":"https:\/\/www.handspeak.com\/word\/h\/headache.mp4","variation_id":0,"video_id":"26838"},{"bbox":[50,6,225,192],"fps":25,"frame_end":-1,"frame_start":1,"instance_id":5,"signer_id":11,"source":"signingsavvy","split":"val","url":"https:\/\/www.signingsavvy.com\/signs\/mp4\/14\/14189.mp4","variation_id":0,"video_id":"26839"},{"bbox":[45,7,228,192],"fps":25,"frame_end":-1,"frame_start":1,"instance_id":6,"signer_id":11,"source":"signingsavvy","split":"train","url":"https:\/\/www.signingsavvy.com\/signs\/mp4\/14\/14190.mp4","variation_id":0,"video_id":"26840"},{"bbox":[317,25,1087,720],"fps":25,"frame_end":-1,"frame_start":1,"instance_id":7,"signer_id":5,"source":"aslu","split":"train","url":"https:\/\/www.youtube.com\/watch?v=4hjOQ8h1sBY","variation_id":0,"video_id":"26841"},{"bbox":[210,30,515,370],"fps":25,"frame_end":-1,"frame_start":1,"instance_id":8,"signer_id":91,"source":"aslsignbank","split":"train","url":"https:\/\/aslsignbank.haskins.yale.edu\/dictionary\/protected_media\/glossvideo\/ASL\/HE\/HEADACHE-1997.mp4","variation_id":0,"video_id":"65881"},{"bbox":[86,5,407,360],"fps":25,"frame_end":-1,"frame_start":1,"instance_id":9,"signer_id":109,"source":"asllex","split":"train","url":"https:\/\/youtu.be\/9CyEdCrk9ag","variation_id":0,"video_id":"67747"},{"bbox":[346,28,1051,720],"fps":25,"frame_end":-1,"frame_start":1,"instance_id":10,"signer_id":5,"source":"aslu","split":"val","url":"https:\/\/www.youtube.com\/watch?v=BNPsGAjo6nI","variation_id":0,"video_id":"26842"},{"bbox":[274,50,978,720],"fps":25,"frame_end":-1,"frame_start":1,"instance_id":11,"signer_id":5,"source":"aslu","split":"train","url":"https:\/\/www.youtube.com\/watch?v=hCePLZW65pQ","variation_id":0,"video_id":"26843"},{"bbox":[291,16,1074,720],"fps":25,"frame_end":-1,"frame_start":1,"instance_id":12,"signer_id":5,"source":"aslu","split":"train","url":"https:\/\/www.youtube.com\/watch?v=ZnwxFOv3SD8","variation_id":0,"video_id":"26844"},{"bbox":[0,0,256,240],"fps":25,"frame_end":-1,"frame_start":1,"instance_id":13,"signer_id":44,"source":"aslpro","split":"train","url":"http:\/\/www.aslpro.com\/\/main\/h\/headache.swf","variation_id":0,"video_id":"26845"},{"bbox":[149,55,571,400],"fps":25,"frame_end":-1,"frame_start":1,"instance_id":14,"signer_id":12,"source":"aslsearch","split":"train","url":"http:\/\/www.aslsearch.com\/signs\/videos\/headache.mp4","variation_id":0,"video_id":"26846"},{"bbox":[27,0,294,240],"fps":25,"frame_end":-1,"frame_start":1,"instance_id":15,"signer_id":37,"source":"spreadthesign","split":"train","url":"https:\/\/media.spreadthesign.com\/video\/mp4\/13\/456563.mp4","variation_id":0,"video_id":"26833"},{"bbox":[424,58,827,720],"fps":25,"frame_end":-1,"frame_start":1,"instance_id":16,"signer_id":38,"source":"startasl","split":"train","url":"https:\/\/s3-us-west-1.amazonaws.com\/files.startasl.com\/asldictionary\/headache.mp4","variation_id":0,"video_id":"26834"}]},{"gloss":"cold","instances":[{"bbox":[129,16,476,370],"fps":25,"frame_end":-1,"frame_start":1,"instance_id":0,"signer_id":99,"source":"aslsignbank","split":"test","url":"https:\/\/aslsignbank.haskins.yale.edu\/dictionary\/protected_media\/glossvideo\/ASL\/CO\/COLD-432.mp4","variation_id":0,"video_id":"65377"},{"bbox":[180,57,551,400],"fps":25,"frame_end":-1,"frame_start":1,"instance_id":1,"signer_id":12,"source":"aslsearch","split":"test","url":"http:\/\/www.aslsearch.com\/signs\/videos\/cold.mp4","variation_id":0,"video_id":"11638"},{"bbox":[210,16,540,414],"fps":25,"frame_end":-1,"frame_start":1,"instance_id":2,"signer_id":36,"source":"startasl","split":"train","url":"https:\/\/s3-us-west-1.amazonaws.com\/files.startasl.com\/asldictionary\/cold.mp4","variation_id":0,"video_id":"11622"},{"bbox":[380,16,825,480],"fps":25,"frame_end":-1,"frame_start":1,"instance_id":3,"signer_id":52,"source":"signschool","split":"train","url":"https:\/\/signstock.blob.core.windows.net\/signschool\/videos\/db_uploads\/SignSchool%20cold%203-YldGtQZmZYU.mp4","variation_id":0,"video_id":"11623"},{"bbox":[593,70,1468,1080],"fps":25,"frame_end":-1,"frame_start":1,"instance_id":4,"signer_id":6,"source":"signschool","split":"train","url":"https:\/\/signstock.blob.core.windows.net\/signschool\/videos\/db_uploads\/SignSchool%20Cold-u2a1DwJhmrQ.mp4","variation_id":0,"video_id":"11624"},{"bbox":[624,133,1621,1072],"fps":25,"frame_end":-1,"frame_start":1,"instance_id":5,"signer_id":39,"source":"signschool","split":"val","url":"https:\/\/signstock.blob.core.windows.net\/signschool\/videos\/db_uploads\/SignSchool%20Cold-V5nv_yk_Ah8.mp4","variation_id":0,"video_id":"11625"},{"bbox":[411,31,1128,720],"fps":25,"frame_end":-1,"frame_start":1,"instance_id":7,"signer_id":4,"source":"signschool","split":"train","url":"https:\/\/signstock.blob.core.windows.net\/signschool\/videos\/SignSchool%20Cold.mp4","variation_id":0,"video_id":"11627"},{"bbox":[116,29,513,480],"fps":25,"frame_end":-1,"frame_start":1,"instance_id":8,"signer_id":59,"source":"asldeafined","split":"val","url":"https:\/\/media.asldeafined.com\/vocabulary\/1466899767.7689.mp4","variation_id":0,"video_id":"11628"},{"bbox":[110,0,584,480],"fps":25,"frame_end":-1,"frame_start":1,"instance_id":10,"signer_id":20,"source":"handspeak","split":"train","url":"https:\/\/www.handspeak.com\/word\/c\/cold-brr.mp4","variation_id":0,"video_id":"11630"},{"bbox":[59,16,263,240],"fps":25,"frame_end":-1,"frame_start":1,"instance_id":11,"signer_id":56,"source":"spreadthesign","split":"train","url":"https:\/\/media.spreadthesign.com\/video\/mp4\/13\/399313.mp4","variation_id":0,"video_id":"11621"},{"bbox":[103,20,387,360],"fps":25,"frame_end":-1,"frame_start":1,"instance_id":12,"signer_id":109,"source":"asllex","split":"train","url":"https:\/\/youtu.be\/EQJ7BYa01Co","variation_id":0,"video_id":"67513"},{"bbox":[88,22,216,192],"fps":25,"frame_end":-1,"frame_start":1,"instance_id":15,"signer_id":10,"source":"signingsavvy","split":"train","url":"https:\/\/www.signingsavvy.com\/signs\/mp4\/22\/22759.mp4","variation_id":0,"video_id":"11633"},{"bbox":[65,21,233,192],"fps":25,"frame_end":-1,"frame_start":1,"instance_id":16,"signer_id":10,"source":"signingsavvy","split":"val","url":"https:\/\/www.signingsavvy.com\/signs\/mp4\/22\/22867.mp4","variation_id":0,"video_id":"11634"},{"bbox":[79,16,221,192],"fps":25,"frame_end":-1,"frame_start":1,"instance_id":17,"signer_id":11,"source":"signingsavvy","split":"train","url":"https:\/\/www.signingsavvy.com\/signs\/mp4\/7\/7159.mp4","variation_id":0,"video_id":"11635"},{"bbox":[219,84,932,720],"fps":25,"frame_end":-1,"frame_start":1,"instance_id":18,"signer_id":65,"source":"nabboud","split":"train","url":"https:\/\/www.youtube.com\/watch?v=trlv3hkAQsQ","variation_id":0,"video_id":"11636"},{"bbox":[14,1,221,240],"fps":25,"frame_end":-1,"frame_start":1,"instance_id":19,"signer_id":72,"source":"aslpro","split":"train","url":"http:\/\/www.aslpro.com\/main\/c\/cold.swf","variation_id":0,"video_id":"11637"}]},{"gloss":"tired","instances":[{"bbox":[0,0,360,240],"fps":25,"frame_end":3064,"frame_start":2978,"instance_id":0,"signer_id":9,"source":"asl5200","split":"test","url":"https:\/\/www.youtube.com\/watch?v=x6CehcknaH8","variation_id":0,"video_id":"58588"},{"bbox":[103,11,567,360],"fps":25,"frame_end":60,"frame_start":1,"instance_id":1,"signer_id":112,"source":"lillybauer","split":"test","url":"https:\/\/www.youtube.com\/watch?v=gm7e09gL4_g","variation_id":0,"video_id":"68488"},{"bbox":[322,11,1087,720],"fps":25,"frame_end":-1,"frame_start":1,"instance_id":2,"signer_id":109,"source":"valencia-asl","split":"train","url":"https:\/\/www.youtube.com\/watch?v=qdC7SfVp8iQ","variation_id":0,"video_id":"68172"},{"bbox":[66,0,623,480],"fps":25,"frame_end":-1,"frame_start":1,"instance_id":3,"signer_id":13,"source":"asldeafined","split":"train","url":"https:\/\/media.asldeafined.com\/vocabulary\/1468945582.6285.mp4","variation_id":0,"video_id":"58594"},{"bbox":[96,0,541,480],"fps":25,"frame_end":-1,"frame_start":1,"instance_id":4,"signer_id":14,"source":"handspeak","split":"train","url":"https:\/\/www.handspeak.com\/word\/t\/tired.mp4","variation_id":0,"video_id":"58595"},{"bbox":[275,23,1037,720],"fps":25,"frame_end":-1,"frame_start":1,"instance_id":5,"signer_id":5,"source":"aslu","split":"val","url":"https:\/\/www.youtube.com\/watch?v=1RRUK21Xyzw","variation_id":0,"video_id":"58596"},{"bbox":[285,43,924,720],"fps":25,"frame_end":-1,"frame_start":1,"instance_id":6,"signer_id":69,"source":"nabboud","split":"train","url":"https:\/\/www.youtube.com\/watch?v=iDYM464AxEk","variation_id":0,"video_id":"58597"},{"bbox":[36,19,440,360],"fps":25,"frame_end":-1,"frame_start":1,"instance_id":7,"signer_id":109,"source":"asllex","split":"val","url":"https:\/\/youtu.be\/O3KYtygHfpU","variation_id":0,"video_id":"67310"},{"bbox":[286,26,961,720],"fps":25,"frame_end":-1,"frame_start":1,"instance_id":8,"signer_id":5,"source":"aslu","split":"train","url":"https:\/\/www.youtube.com\/watch?v=YS5PgjNNxME","variation_id":0,"video_id":"58598"},{"bbox":[6,17,231,240],"fps":25,"frame_end":-1,"frame_start":1,"instance_id":9,"signer_id":30,"source":"aslpro","split":"train","url":"http:\/\/www.aslpro.com\/main\/t\/tired.swf","variation_id":0,"video_id":"58599"},{"bbox":[179,51,572,400],"fps":25,"frame_end":-1,"frame_start":1,"instance_id":10,"signer_id":12,"source":"aslsearch","split":"train","url":"http:\/\/www.aslsearch.com\/signs\/videos\/exhausted.mp4","variation_id":0,"video_id":"58600"},{"bbox":[36,0,313,240],"fps":25,"frame_end":-1,"frame_start":1,"instance_id":11,"signer_id":56,"source":"spreadthesign","split":"train","url":"https:\/\/media.spreadthesign.com\/video\/mp4\/13\/50878.mp4","variation_id":0,"video_id":"58589"},{"bbox":[410,51,840,720],"fps":25,"frame_end":-1,"frame_start":1,"instance_id":12,"signer_id":38,"source":"startasl","split":"val","url":"https:\/\/s3-us-west-1.amazonaws.com\/files.startasl.com\/asldictionary\/tired.mp4","variation_id":0,"video_id":"58590"},{"bbox":[337,22,809,480],"fps":25,"frame_end":-1,"frame_start":1,"instance_id":13,"signer_id":60,"source":"signschool","split":"train","url":"https:\/\/signstock.blob.core.windows.net\/signschool\/videos\/db_uploads\/SignSchool%20tired--IXJYyWRLKU.mp4","variation_id":0,"video_id":"58591"},{"bbox":[282,1,1430,1080],"fps":25,"frame_end":-1,"frame_start":1,"instance_id":14,"signer_id":46,"source":"signschool","split":"train","url":"https:\/\/signstock.blob.core.windows.net\/signschool\/videos\/db_uploads\/SignSchool%20Tired-QFUlgHrzrI8.mp4","variation_id":0,"video_id":"58592"},{"bbox":[709,141,1674,1080],"fps":25,"frame_end":-1,"frame_start":1,"instance_id":15,"signer_id":39,"source":"signschool","split":"train","url":"https:\/\/signstock.blob.core.windows.net\/signschool\/videos\/db_uploads\/SignSchool%20Tired-UrUrq5kVmxo.mp4","variation_id":0,"video_id":"58593"}]},{"gloss":"cough","instances":[{"bbox":[0,0,360,240],"fps":25,"frame_end":6426,"frame_start":6374,"instance_id":0,"signer_id":9,"source":"asl5200","split":"train","url":"https:\/\/www.youtube.com\/watch?v=PPmQd2zWdP0","variation_id":0,"video_id":"13467"},{"bbox":[64,9,211,192],"fps":25,"frame_end":-1,"frame_start":1,"instance_id":1,"signer_id":11,"source":"signingsavvy","split":"train","url":"https:\/\/www.signingsavvy.com\/signs\/mp4\/14\/14188.mp4","variation_id":0,"video_id":"13473"},{"bbox":[288,58,878,720],"fps":25,"frame_end":-1,"frame_start":1,"instance_id":2,"signer_id":5,"source":"aslu","split":"train","url":"https:\/\/www.youtube.com\/watch?v=5GZ1yv24OII","variation_id":0,"video_id":"13474"},{"bbox":[333,36,935,720],"fps":25,"frame_end":-1,"frame_start":1,"instance_id":3,"signer_id":5,"source":"aslu","split":"val","url":"https:\/\/www.youtube.com\/watch?v=UUq9vik7gPw","variation_id":0,"video_id":"13475"},{"bbox":[307,33,939,720],"fps":25,"frame_end":-1,"frame_start":1,"instance_id":4,"signer_id":5,"source":"aslu","split":"train","url":"https:\/\/www.youtube.com\/watch?v=zcA5rEB5KIs","variation_id":0,"video_id":"13476"},{"bbox":[171,16,492,370],"fps":25,"frame_end":-1,"frame_start":1,"instance_id":5,"signer_id":102,"source":"aslsignbank","split":"train","url":"https:\/\/aslsignbank.haskins.yale.edu\/dictionary\/protected_media\/glossvideo\/ASL\/CO\/COUGH-1169.mp4","variation_id":0,"video_id":"65411"},{"bbox":[96,19,381,360],"fps":25,"frame_end":-1,"frame_start":1,"instance_id":6,"signer_id":109,"source":"asllex","split":"train","url":"https:\/\/youtu.be\/kpLPR6He6dg","variation_id":0,"video_id":"67532"},{"bbox":[0,17,218,240],"fps":25,"frame_end":-1,"frame_start":1,"instance_id":7,"signer_id":30,"source":"aslpro","split":"train","url":"http:\/\/www.aslpro.com\/main\/c\/cough.swf","variation_id":0,"video_id":"13477"},{"bbox":[174,64,549,400],"fps":25,"frame_end":-1,"frame_start":1,"instance_id":8,"signer_id":12,"source":"aslsearch","split":"train","url":"http:\/\/www.aslsearch.com\/signs\/videos\/cough.mp4","variation_id":0,"video_id":"13478"},{"bbox":[66,35,235,240],"fps":25,"frame_end":-1,"frame_start":1,"instance_id":9,"signer_id":2,"source":"spreadthesign","split":"test","url":"https:\/\/media.spreadthesign.com\/video\/mp4\/13\/93256.mp4","variation_id":0,"video_id":"13468"},{"bbox":[399,57,812,720],"fps":25,"frame_end":-1,"frame_start":1,"instance_id":10,"signer_id":38,"source":"startasl","split":"val","url":"https:\/\/s3-us-west-1.amazonaws.com\/files.startasl.com\/asldictionary\/cough.mp4","variation_id":0,"video_id":"13469"},{"bbox":[104,28,512,480],"fps":25,"frame_end":-1,"frame_start":1,"instance_id":11,"signer_id":59,"source":"asldeafined","split":"test","url":"https:\/\/media.asldeafined.com\/vocabulary\/1466903703.2205.mp4","variation_id":0,"video_id":"13470"},{"bbox":[62,9,249,240],"fps":25,"frame_end":-1,"frame_start":1,"instance_id":12,"signer_id":14,"source":"handspeak","split":"train","url":"https:\/\/www.handspeak.com\/word\/c\/cough2.mp4","variation_id":0,"video_id":"13471"},{"bbox":[62,8,248,240],"fps":25,"frame_end":-1,"frame_start":1,"instance_id":13,"signer_id":14,"source":"handspeak","split":"train","url":"https:\/\/www.handspeak.com\/word\/c\/cough.mp4","variation_id":0,"video_id":"13472"}]},{"gloss":"heart","instances":[{"bbox":[0,0,360,240],"fps":25,"frame_end":1113,"frame_start":1057,"instance_id":0,"signer_id":9,"source":"asl5200","split":"test","url":"https:\/\/www.youtube.com\/watch?v=SiBub8VD5wo","variation_id":0,"video_id":"27013"},{"bbox":[675,55,1512,1069],"fps":25,"frame_end":-1,"frame_start":1,"instance_id":1,"signer_id":4,"source":"signschool","split":"val","url":"https:\/\/signstock.blob.core.windows.net\/signschool\/videos\/db_uploads\/SignSchool%20Heart%20copy-ruzHjYmh9Yw.mp4","variation_id":0,"video_id":"27044"},{"bbox":[93,12,531,480],"fps":25,"frame_end":-1,"frame_start":1,"instance_id":3,"signer_id":21,"source":"asldeafined","split":"train","url":"https:\/\/media.asldeafined.com\/vocabulary\/1468580452.623.mp4","variation_id":0,"video_id":"27046"},{"bbox":[89,0,588,480],"fps":25,"frame_end":-1,"frame_start":1,"instance_id":4,"signer_id":20,"source":"handspeak","split":"test","url":"https:\/\/www.handspeak.com\/word\/h\/heart2.mp4","variation_id":1,"video_id":"27047"},{"bbox":[123,0,552,480],"fps":25,"frame_end":-1,"frame_start":1,"instance_id":5,"signer_id":20,"source":"handspeak","split":"train","url":"https:\/\/www.handspeak.com\/word\/h\/heart.mp4","variation_id":0,"video_id":"27048"},{"bbox":[87,14,231,192],"fps":25,"frame_end":-1,"frame_start":1,"instance_id":7,"signer_id":11,"source":"signingsavvy","split":"train","url":"https:\/\/www.signingsavvy.com\/signs\/mp4\/8\/8387.mp4","variation_id":0,"video_id":"27050"},{"bbox":[81,14,236,192],"fps":25,"frame_end":-1,"frame_start":1,"instance_id":8,"signer_id":11,"source":"signingsavvy","split":"val","url":"https:\/\/www.signingsavvy.com\/signs\/mp4\/8\/8388.mp4","variation_id":1,"video_id":"27051"},{"bbox":[61,0,264,240],"fps":25,"frame_end":-1,"frame_start":1,"instance_id":9,"signer_id":37,"source":"spreadthesign","split":"train","url":"https:\/\/media.spreadthesign.com\/video\/mp4\/13\/456569.mp4","variation_id":1,"video_id":"27042"},{"bbox":[95,20,394,360],"fps":25,"frame_end":-1,"frame_start":1,"instance_id":10,"signer_id":109,"source":"asllex","split":"train","url":"https:\/\/youtu.be\/0jSUF1b4YiU","variation_id":1,"video_id":"67752"},{"bbox":[160,4,492,360],"fps":25,"frame_end":-1,"frame_start":1,"instance_id":12,"signer_id":5,"source":"aslu","split":"train","url":"https:\/\/www.youtube.com\/watch?v=t6qHzKr2t2s","variation_id":0,"video_id":"27053"},{"bbox":[0,5,217,240],"fps":25,"frame_end":-1,"frame_start":1,"instance_id":14,"signer_id":44,"source":"aslpro","split":"train","url":"http:\/\/www.aslpro.com\/main\/h\/heart.swf","variation_id":1,"video_id":"27055"},{"bbox":[182,52,559,400],"fps":25,"frame_end":-1,"frame_start":1,"instance_id":15,"signer_id":12,"source":"aslsearch","split":"train","url":"http:\/\/www.aslsearch.com\/signs\/videos\/heart2.mp4","variation_id":1,"video_id":"27056"},{"bbox":[192,60,563,400],"fps":25,"frame_end":-1,"frame_start":1,"instance_id":16,"signer_id":12,"source":"aslsearch","split":"train","url":"http:\/\/www.aslsearch.com\/signs\/videos\/heart.mp4","variation_id":0,"video_id":"27057"},{"bbox":[670,51,1580,1078],"fps":25,"frame_end":-1,"frame_start":1,"instance_id":17,"signer_id":4,"source":"signschool","split":"train","url":"https:\/\/signstock.blob.core.windows.net\/signschool\/videos\/db_uploads\/SignSchool%20Heart%202-HROvaYjDSms.mp4","variation_id":1,"video_id":"27043"}]},{"gloss":"thank you","instances":[{"bbox":[0,0,360,240],"fps":25,"frame_end":1471,"frame_start":1425,"instance_id":0,"signer_id":9,"source":"asl5200","split":"train","url":"https:\/\/www.youtube.com\/watch?v=x6CehcknaH8","variation_id":0,"video_id":"57653"},{"bbox":[378,42,896,720],"fps":25,"frame_end":-1,"frame_start":1,"instance_id":1,"signer_id":115,"source":"aslbrick","split":"train","url":"http:\/\/aslbricks.org\/New\/ASL-Videos\/thank%20you.mp4","variation_id":0,"video_id":"69502"},{"bbox":[321,22,916,720],"fps":25,"frame_end":39,"frame_start":1,"instance_id":2,"signer_id":115,"source":"lillybauer","split":"train","url":"https:\/\/www.youtube.com\/watch?v=pj0YH_l8TNM","variation_id":0,"video_id":"68796"},{"bbox":[320,0,835,720],"fps":25,"frame_end":-1,"frame_start":1,"instance_id":6,"signer_id":82,"source":"scott","split":"val","url":"https:\/\/www.youtube.com\/watch?v=7XHOmZYiBew","variation_id":0,"video_id":"57663"},{"bbox":[380,73,852,720],"fps":25,"frame_end":-1,"frame_start":1,"instance_id":7,"signer_id":51,"source":"nabboud","split":"train","url":"https:\/\/www.youtube.com\/watch?v=lJXvGI7r_Fc","variation_id":0,"video_id":"57664"},{"bbox":[180,31,459,370],"fps":25,"frame_end":-1,"frame_start":1,"instance_id":8,"signer_id":98,"source":"aslsignbank","split":"train","url":"https:\/\/aslsignbank.haskins.yale.edu\/dictionary\/protected_media\/glossvideo\/ASL\/TH\/THANK-YOU-1198.mp4","variation_id":0,"video_id":"66598"},{"bbox":[697,39,1522,1067],"fps":25,"frame_end":-1,"frame_start":1,"instance_id":9,"signer_id":46,"source":"signschool","split":"train","url":"https:\/\/signstock.blob.core.windows.net\/signschool\/videos\/db_uploads\/SignSchool%20ThankYou-OGQTouYS3zM.mp4","variation_id":0,"video_id":"57655"},{"bbox":[376,73,876,720],"fps":25,"frame_end":-1,"frame_start":1,"instance_id":10,"signer_id":51,"source":"nabboud","split":"train","url":"https:\/\/www.youtube.com\/watch?v=sH87G_Bz_nA","variation_id":0,"video_id":"57665"},{"bbox":[356,72,871,720],"fps":25,"frame_end":-1,"frame_start":1,"instance_id":11,"signer_id":51,"source":"nabboud","split":"train","url":"https:\/\/www.youtube.com\/watch?v=t8Hr0IHghrQ","variation_id":0,"video_id":"57666"},{"bbox":[168,54,537,400],"fps":25,"frame_end":-1,"frame_start":1,"instance_id":12,"signer_id":12,"source":"aslsearch","split":"test","url":"http:\/\/www.aslsearch.com\/signs\/videos\/thank.mp4","variation_id":0,"video_id":"57667"},{"bbox":[144,0,521,480],"fps":25,"frame_end":-1,"frame_start":1,"instance_id":13,"signer_id":13,"source":"asldeafined","split":"val","url":"https:\/\/media.asldeafined.com\/vocabulary\/1468944231.2757.mp4","variation_id":0,"video_id":"57656"},{"bbox":[147,32,521,480],"fps":25,"frame_end":-1,"frame_start":1,"instance_id":14,"signer_id":15,"source":"asldeafined","split":"test","url":"https:\/\/media.asldeafined.com\/vocabulary\/1522767348.9440.mp4","variation_id":0,"video_id":"57657"},{"bbox":[137,9,466,360],"fps":25,"frame_end":-1,"frame_start":1,"instance_id":15,"signer_id":14,"source":"handspeak","split":"train","url":"https:\/\/www.handspeak.com\/word\/t\/thank.mp4","variation_id":0,"video_id":"57658"},{"bbox":[85,11,223,192],"fps":25,"frame_end":-1,"frame_start":1,"instance_id":16,"signer_id":11,"source":"signingsavvy","split":"train","url":"https:\/\/www.signingsavvy.com\/signs\/mp4\/14\/14353.mp4","variation_id":0,"video_id":"57659"}]},{"gloss":"vomit","instances":[{"bbox":[0,0,360,240],"fps":25,"frame_end":1048,"frame_start":996,"instance_id":0,"signer_id":9,"source":"asl5200","split":"train","url":"https:\/\/www.youtube.com\/watch?v=cP1FdT_zo7U","variation_id":0,"video_id":"61977"},{"bbox":[706,72,1605,1077],"fps":25,"frame_end":-1,"frame_start":1,"instance_id":1,"signer_id":32,"source":"signschool","split":"train","url":"https:\/\/signstock.blob.core.windows.net\/signschool\/videos\/db_uploads\/SignSchool%20Puke%2C%20Vomit-RRGvr-dhQHo.mp4","variation_id":0,"video_id":"61982"},{"bbox":[344,35,753,480],"fps":25,"frame_end":-1,"frame_start":1,"instance_id":2,"signer_id":60,"source":"signschool","split":"train","url":"https:\/\/signstock.blob.core.windows.net\/signschool\/videos\/db_uploads\/SignSchool%20Throwing%20Up-q7oFG6PzyxQ.mp4","variation_id":0,"video_id":"61983"},{"bbox":[144,0,519,480],"fps":25,"frame_end":-1,"frame_start":1,"instance_id":3,"signer_id":13,"source":"asldeafined","split":"val","url":"https:\/\/media.asldeafined.com\/vocabulary\/1468926788.2550.mp4","variation_id":0,"video_id":"61984"},{"bbox":[91,8,546,480],"fps":25,"frame_end":-1,"frame_start":1,"instance_id":4,"signer_id":14,"source":"handspeak","split":"train","url":"https:\/\/www.handspeak.com\/word\/v\/vomit.mp4","variation_id":0,"video_id":"61985"},{"bbox":[79,13,223,192],"fps":25,"frame_end":-1,"frame_start":1,"instance_id":5,"signer_id":11,"source":"signingsavvy","split":"train","url":"https:\/\/www.signingsavvy.com\/signs\/mp4\/7\/7819.mp4","variation_id":0,"video_id":"61986"},{"bbox":[88,20,375,360],"fps":25,"frame_end":-1,"frame_start":1,"instance_id":6,"signer_id":109,"source":"asllex","split":"train","url":"https:\/\/youtu.be\/Vfxe3bvoKdY","variation_id":0,"video_id":"67033"},{"bbox":[78,16,212,192],"fps":25,"frame_end":-1,"frame_start":1,"instance_id":7,"signer_id":11,"source":"signingsavvy","split":"train","url":"https:\/\/www.signingsavvy.com\/signs\/mp4\/9\/9190.mp4","variation_id":0,"video_id":"61987"},{"bbox":[345,40,939,720],"fps":25,"frame_end":-1,"frame_start":1,"instance_id":8,"signer_id":5,"source":"aslu","split":"train","url":"https:\/\/www.youtube.com\/watch?v=eyu6rDm1uFM","variation_id":0,"video_id":"61988"},{"bbox":[28,15,230,240],"fps":25,"frame_end":-1,"frame_start":1,"instance_id":9,"signer_id":87,"source":"aslpro","split":"test","url":"http:\/\/www.aslpro.com\/main\/v\/vomit.swf","variation_id":0,"video_id":"61989"},{"bbox":[239,40,488,400],"fps":25,"frame_end":-1,"frame_start":1,"instance_id":10,"signer_id":41,"source":"aslsearch","split":"val","url":"http:\/\/www.aslsearch.com\/signs\/videos\/vomit.mp4","variation_id":0,"video_id":"61990"},{"bbox":[62,9,280,240],"fps":25,"frame_end":-1,"frame_start":1,"instance_id":11,"signer_id":28,"source":"spreadthesign","split":"test","url":"https:\/\/media.spreadthesign.com\/video\/mp4\/13\/483787.mp4","variation_id":0,"video_id":"61978"},{"bbox":[407,51,805,720],"fps":25,"frame_end":-1,"frame_start":1,"instance_id":12,"signer_id":38,"source":"startasl","split":"train","url":"https:\/\/s3-us-west-1.amazonaws.com\/files.startasl.com\/asldictionary\/vomit.mp4","variation_id":0,"video_id":"61979"},{"bbox":[728,75,1599,1076],"fps":25,"frame_end":-1,"frame_start":1,"instance_id":13,"signer_id":32,"source":"signschool","split":"train","url":"https:\/\/signstock.blob.core.windows.net\/signschool\/videos\/db_uploads\/SignSchool%20Puke%2C%20Vomit%202-bjEi_7qYcBQ.mp4","variation_id":0,"video_id":"61980"}]},{"gloss":"hurt","instances":[{"bbox":[0,0,360,240],"fps":25,"frame_end":2752,"frame_start":2716,"instance_id":0,"signer_id":9,"source":"asl5200","split":"train","url":"https:\/\/www.youtube.com\/watch?v=SiBub8VD5wo","variation_id":0,"video_id":"28438"},{"bbox":[122,21,508,480],"fps":25,"frame_end":6562,"frame_start":6429,"instance_id":1,"signer_id":121,"source":"northtexas","split":"train","url":"https:\/\/www.youtube.com\/watch?v=VwejDy96MzM","variation_id":0,"video_id":"70147"},{"bbox":[352,22,779,480],"fps":25,"frame_end":-1,"frame_start":1,"instance_id":2,"signer_id":60,"source":"signschool","split":"train","url":"https:\/\/signstock.blob.core.windows.net\/signschool\/videos\/db_uploads\/SignSchool%20Hurt-_st2tPdAvgQ.mp4","variation_id":0,"video_id":"28441"},{"bbox":[80,0,589,480],"fps":25,"frame_end":-1,"frame_start":1,"instance_id":4,"signer_id":20,"source":"handspeak","split":"val","url":"https:\/\/www.handspeak.com\/word\/h\/hurt2.mp4","variation_id":0,"video_id":"28443"},{"bbox":[79,0,589,480],"fps":25,"frame_end":-1,"frame_start":1,"instance_id":5,"signer_id":20,"source":"handspeak","split":"train","url":"https:\/\/www.handspeak.com\/word\/h\/hurt.mp4","variation_id":0,"video_id":"28444"},{"bbox":[58,14,228,192],"fps":25,"frame_end":-1,"frame_start":1,"instance_id":6,"signer_id":10,"source":"signingsavvy","split":"train","url":"https:\/\/www.signingsavvy.com\/signs\/mp4\/23\/23773.mp4","variation_id":0,"video_id":"28445"},{"bbox":[75,15,221,192],"fps":25,"frame_end":-1,"frame_start":1,"instance_id":7,"signer_id":10,"source":"signingsavvy","split":"train","url":"https:\/\/www.signingsavvy.com\/signs\/mp4\/23\/23774.mp4","variation_id":0,"video_id":"28446"},{"bbox":[316,55,898,720],"fps":25,"frame_end":-1,"frame_start":1,"instance_id":11,"signer_id":69,"source":"nabboud","split":"train","url":"https:\/\/www.youtube.com\/watch?v=Ekcn4CILyfo","variation_id":0,"video_id":"28450"},{"bbox":[282,59,936,720],"fps":25,"frame_end":-1,"frame_start":1,"instance_id":13,"signer_id":5,"source":"aslu","split":"val","url":"https:\/\/www.youtube.com\/watch?v=xs4k_Qf3BSc","variation_id":0,"video_id":"28452"},{"bbox":[0,9,258,240],"fps":25,"frame_end":-1,"frame_start":1,"instance_id":14,"signer_id":25,"source":"aslpro","split":"test","url":"http:\/\/www.aslpro.com\/main\/h\/hurt.swf","variation_id":0,"video_id":"28453"},{"bbox":[201,53,552,400],"fps":25,"frame_end":-1,"frame_start":1,"instance_id":15,"signer_id":12,"source":"aslsearch","split":"test","url":"http:\/\/www.aslsearch.com\/signs\/videos\/sore.mp4","variation_id":0,"video_id":"28454"},{"bbox":[182,18,552,414],"fps":25,"frame_end":-1,"frame_start":1,"instance_id":17,"signer_id":36,"source":"startasl","split":"train","url":"https:\/\/s3-us-west-1.amazonaws.com\/files.startasl.com\/asldictionary\/hurt.mp4","variation_id":0,"video_id":"28440"}]},{"gloss":"stomach","instances":[{"bbox":[0,0,360,240],"fps":25,"frame_end":9003,"frame_start":8947,"instance_id":0,"signer_id":9,"source":"asl5200","split":"train","url":"https:\/\/www.youtube.com\/watch?v=XB3Q6IX6CBo","variation_id":0,"video_id":"54870"},{"bbox":[5,18,222,240],"fps":25,"frame_end":-1,"frame_start":1,"instance_id":1,"signer_id":87,"source":"aslpro","split":"train","url":"http:\/\/www.aslpro.com\/main\/s\/stomach.swf","variation_id":0,"video_id":"54885"},{"bbox":[202,49,566,400],"fps":25,"frame_end":-1,"frame_start":1,"instance_id":2,"signer_id":12,"source":"aslsearch","split":"train","url":"http:\/\/www.aslsearch.com\/signs\/videos\/stomach.mp4","variation_id":0,"video_id":"54886"},{"bbox":[199,30,474,370],"fps":25,"frame_end":-1,"frame_start":1,"instance_id":3,"signer_id":100,"source":"aslsignbank","split":"val","url":"https:\/\/aslsignbank.haskins.yale.edu\/dictionary\/protected_media\/glossvideo\/ASL\/ST\/STOMACH-1128.mp4","variation_id":0,"video_id":"66560"},{"bbox":[42,9,240,240],"fps":25,"frame_end":-1,"frame_start":1,"instance_id":4,"signer_id":26,"source":"spreadthesign","split":"train","url":"https:\/\/media.spreadthesign.com\/video\/mp4\/13\/310766.mp4","variation_id":0,"video_id":"54878"},{"bbox":[77,24,379,360],"fps":25,"frame_end":-1,"frame_start":1,"instance_id":5,"signer_id":109,"source":"asllex","split":"train","url":"https:\/\/youtu.be\/cSuk-U74vPM","variation_id":0,"video_id":"67248"},{"bbox":[713,137,1547,1065],"fps":25,"frame_end":-1,"frame_start":1,"instance_id":6,"signer_id":31,"source":"signschool","split":"train","url":"https:\/\/signstock.blob.core.windows.net\/signschool\/videos\/db_uploads\/SignSchool%20Stomach-7_C30DpQkhM.mp4","variation_id":0,"video_id":"54879"},{"bbox":[103,0,565,480],"fps":25,"frame_end":-1,"frame_start":1,"instance_id":7,"signer_id":13,"source":"asldeafined","split":"train","url":"https:\/\/media.asldeafined.com\/vocabulary\/1468896442.4103.mp4","variation_id":0,"video_id":"54880"},{"bbox":[43,0,258,240],"fps":25,"frame_end":-1,"frame_start":1,"instance_id":8,"signer_id":20,"source":"handspeak","split":"val","url":"https:\/\/www.handspeak.com\/word\/s\/stomach.mp4","variation_id":0,"video_id":"54881"},{"bbox":[68,14,214,192],"fps":25,"frame_end":-1,"frame_start":1,"instance_id":9,"signer_id":10,"source":"signingsavvy","split":"test","url":"https:\/\/www.signingsavvy.com\/signs\/mp4\/23\/23860.mp4","variation_id":0,"video_id":"54882"},{"bbox":[60,13,211,192],"fps":25,"frame_end":-1,"frame_start":1,"instance_id":10,"signer_id":10,"source":"signingsavvy","split":"test","url":"https:\/\/www.signingsavvy.com\/signs\/mp4\/23\/23861.mp4","variation_id":0,"video_id":"54883"},{"bbox":[289,37,934,720],"fps":25,"frame_end":-1,"frame_start":1,"instance_id":11,"signer_id":5,"source":"aslu","split":"train","url":"https:\/\/www.youtube.com\/watch?v=KJLt7QN7K4Q","variation_id":0,"video_id":"54884"}]},{"gloss":"allergy","instances":[{"bbox":[170,10,492,370],"fps":25,"frame_end":-1,"frame_start":1,"instance_id":0,"signer_id":95,"source":"aslsignbank","split":"train","url":"https:\/\/aslsignbank.haskins.yale.edu\/dictionary\/protected_media\/glossvideo\/ASL\/AL\/ALLERGY-2881.mp4","variation_id":0,"video_id":"65050"},{"bbox":[41,11,237,192],"fps":25,"frame_end":-1,"frame_start":1,"instance_id":1,"signer_id":11,"source":"signingsavvy","split":"train","url":"https:\/\/www.signingsavvy.com\/signs\/mp4\/5\/5321.mp4","variation_id":0,"video_id":"01962"},{"bbox":[4,13,217,240],"fps":25,"frame_end":-1,"frame_start":1,"instance_id":3,"signer_id":24,"source":"aslpro","split":"train","url":"http:\/\/www.aslpro.com\/main\/a\/allergy.swf","variation_id":0,"video_id":"01964"},{"bbox":[145,7,523,370],"fps":25,"frame_end":-1,"frame_start":1,"instance_id":4,"signer_id":95,"source":"aslsignbank","split":"val","url":"https:\/\/aslsignbank.haskins.yale.edu\/dictionary\/protected_media\/glossvideo\/ASL\/AL\/ALLERGY-2885.mp4","variation_id":0,"video_id":"65051"},{"bbox":[65,27,260,240],"fps":25,"frame_end":-1,"frame_start":1,"instance_id":5,"signer_id":2,"source":"spreadthesign","split":"train","url":"https:\/\/media.spreadthesign.com\/video\/mp4\/13\/91688.mp4","variation_id":0,"video_id":"01955"},{"bbox":[243,36,554,400],"fps":25,"frame_end":-1,"frame_start":1,"instance_id":6,"signer_id":41,"source":"aslsearch","split":"val","url":"http:\/\/www.aslsearch.com\/signs\/videos\/allergy.mp4","variation_id":0,"video_id":"01965"},{"bbox":[343,43,1065,720],"fps":25,"frame_end":-1,"frame_start":1,"instance_id":7,"signer_id":31,"source":"signschool","split":"train","url":"https:\/\/signstock.blob.core.windows.net\/signschool\/videos\/SignSchool%20Allergy.mp4","variation_id":0,"video_id":"01956"},{"bbox":[36,22,527,480],"fps":25,"frame_end":-1,"frame_start":1,"instance_id":8,"signer_id":13,"source":"asldeafined","split":"train","url":"https:\/\/media.asldeafined.com\/vocabulary\/1466173011.385.mp4","variation_id":0,"video_id":"01957"},{"bbox":[101,12,574,480],"fps":25,"frame_end":-1,"frame_start":1,"instance_id":10,"signer_id":14,"source":"handspeak","split":"test","url":"https:\/\/www.handspeak.com\/word\/a\/allergy.mp4","variation_id":0,"video_id":"01959"},{"bbox":[38,13,235,192],"fps":25,"frame_end":-1,"frame_start":1,"instance_id":11,"signer_id":11,"source":"signingsavvy","split":"train","url":"https:\/\/www.signingsavvy.com\/signs\/mp4\/0\/522.mp4","variation_id":0,"video_id":"01960"}]},{"gloss":"diarrhea","instances":[{"bbox":[0,0,360,240],"fps":25,"frame_end":2485,"frame_start":2403,"instance_id":0,"signer_id":9,"source":"asl5200","split":"train","url":"https:\/\/www.youtube.com\/watch?v=ChIupJBcxjs","variation_id":0,"video_id":"16095"},{"bbox":[82,44,246,240],"fps":25,"frame_end":-1,"frame_start":1,"instance_id":2,"signer_id":2,"source":"spreadthesign","split":"train","url":"https:\/\/media.spreadthesign.com\/video\/mp4\/13\/91741.mp4","variation_id":0,"video_id":"16097"},{"bbox":[439,60,812,720],"fps":25,"frame_end":-1,"frame_start":1,"instance_id":3,"signer_id":38,"source":"startasl","split":"val","url":"https:\/\/s3-us-west-1.amazonaws.com\/files.startasl.com\/asldictionary\/diarrhea.mp4","variation_id":0,"video_id":"16098"},{"bbox":[491,45,1595,1080],"fps":25,"frame_end":-1,"frame_start":1,"instance_id":4,"signer_id":32,"source":"signschool","split":"train","url":"https:\/\/signstock.blob.core.windows.net\/signschool\/videos\/db_uploads\/SignSchool%20Diarrhea-LE6whMFnueQ.mp4","variation_id":0,"video_id":"16099"},{"bbox":[139,30,525,480],"fps":25,"frame_end":-1,"frame_start":1,"instance_id":5,"signer_id":59,"source":"asldeafined","split":"val","url":"https:\/\/media.asldeafined.com\/vocabulary\/1466909453.5664.mp4","variation_id":0,"video_id":"16100"},{"bbox":[196,35,506,360],"fps":25,"frame_end":-1,"frame_start":1,"instance_id":6,"signer_id":14,"source":"handspeak","split":"train","url":"https:\/\/www.handspeak.com\/word\/d\/diarrhea.mp4","variation_id":0,"video_id":"16101"},{"bbox":[90,14,228,192],"fps":25,"frame_end":-1,"frame_start":1,"instance_id":7,"signer_id":11,"source":"signingsavvy","split":"train","url":"https:\/\/www.signingsavvy.com\/signs\/mp4\/8\/8216.mp4","variation_id":0,"video_id":"16102"},{"bbox":[4,8,250,240],"fps":25,"frame_end":-1,"frame_start":1,"instance_id":8,"signer_id":25,"source":"aslpro","split":"test","url":"http:\/\/www.aslpro.com\/main\/d\/diarrhea.swf","variation_id":0,"video_id":"16103"},{"bbox":[189,60,542,400],"fps":25,"frame_end":-1,"frame_start":1,"instance_id":9,"signer_id":12,"source":"aslsearch","split":"train","url":"http:\/\/www.aslsearch.com\/signs\/videos\/diarrhea.mp4","variation_id":0,"video_id":"16104"}]},{"gloss":"pain","instances":[{"bbox":[0,0,360,240],"fps":25,"frame_end":100,"frame_start":24,"instance_id":0,"signer_id":9,"source":"asl5200","split":"train","url":"https:\/\/www.youtube.com\/watch?v=zHd4YEFzpwE","variation_id":0,"video_id":"40797"},{"bbox":[201,53,552,400],"fps":25,"frame_end":-1,"frame_start":1,"instance_id":1,"signer_id":12,"source":"aslsearch","split":"train","url":"http:\/\/www.aslsearch.com\/signs\/videos\/sore.mp4","variation_id":0,"video_id":"40810"},{"bbox":[10,8,285,240],"fps":25,"frame_end":-1,"frame_start":1,"instance_id":2,"signer_id":0,"source":"spreadthesign","split":"train","url":"https:\/\/media.spreadthesign.com\/video\/mp4\/13\/63555.mp4","variation_id":0,"video_id":"40802"},{"bbox":[79,29,404,360],"fps":25,"frame_end":-1,"frame_start":1,"instance_id":3,"signer_id":109,"source":"asllex","split":"val","url":"https:\/\/youtu.be\/PUeBxtWPPFw","variation_id":0,"video_id":"67956"},{"bbox":[139,0,552,480],"fps":25,"frame_end":-1,"frame_start":1,"instance_id":4,"signer_id":13,"source":"asldeafined","split":"train","url":"https:\/\/media.asldeafined.com\/vocabulary\/1468723103.4644.mp4","variation_id":0,"video_id":"40803"},{"bbox":[107,8,527,480],"fps":25,"frame_end":-1,"frame_start":1,"instance_id":5,"signer_id":14,"source":"handspeak","split":"val","url":"https:\/\/www.handspeak.com\/word\/p\/pain.mp4","variation_id":0,"video_id":"40804"},{"bbox":[58,14,228,192],"fps":25,"frame_end":-1,"frame_start":1,"instance_id":7,"signer_id":10,"source":"signingsavvy","split":"train","url":"https:\/\/www.signingsavvy.com\/signs\/mp4\/23\/23773.mp4","variation_id":0,"video_id":"40806"},{"bbox":[75,15,221,192],"fps":25,"frame_end":-1,"frame_start":1,"instance_id":8,"signer_id":10,"source":"signingsavvy","split":"train","url":"https:\/\/www.signingsavvy.com\/signs\/mp4\/23\/23774.mp4","variation_id":0,"video_id":"40807"},{"bbox":[310,0,1067,720],"fps":25,"frame_end":-1,"frame_start":1,"instance_id":9,"signer_id":5,"source":"aslu","split":"test","url":"https:\/\/www.youtube.com\/watch?v=c-oLk9yPARI","variation_id":0,"video_id":"40808"},{"bbox":[0,7,250,240],"fps":25,"frame_end":-1,"frame_start":1,"instance_id":10,"signer_id":44,"source":"aslpro","split":"train","url":"http:\/\/www.aslpro.com\/main\/p\/pain.swf","variation_id":0,"video_id":"40809"}]},{"gloss":"blood","instances":[{"bbox":[0,0,360,240],"fps":25,"frame_end":3452,"frame_start":3420,"instance_id":0,"signer_id":9,"source":"asl5200","split":"train","url":"https:\/\/www.youtube.com\/watch?v=pDqITge_TGs","variation_id":0,"video_id":"06723"},{"bbox":[188,23,499,370],"fps":25,"frame_end":-1,"frame_start":1,"instance_id":1,"signer_id":90,"source":"aslsignbank","split":"train","url":"https:\/\/aslsignbank.haskins.yale.edu\/dictionary\/protected_media\/glossvideo\/ASL\/BL\/BLOOD-416.mp4","variation_id":0,"video_id":"65212"},{"bbox":[69,0,248,240],"fps":25,"frame_end":-1,"frame_start":1,"instance_id":2,"signer_id":8,"source":"spreadthesign","split":"train","url":"https:\/\/media.spreadthesign.com\/video\/mp4\/13\/455697.mp4","variation_id":0,"video_id":"06733"},{"bbox":[98,19,395,360],"fps":25,"frame_end":-1,"frame_start":1,"instance_id":3,"signer_id":109,"source":"asllex","split":"train","url":"https:\/\/youtu.be\/HG3nIRWzkzQ","variation_id":0,"video_id":"67418"},{"bbox":[124,15,534,480],"fps":25,"frame_end":-1,"frame_start":1,"instance_id":4,"signer_id":59,"source":"asldeafined","split":"val","url":"https:\/\/media.asldeafined.com\/vocabulary\/1466682901.3647.mp4","variation_id":0,"video_id":"06734"},{"bbox":[77,2,542,480],"fps":25,"frame_end":-1,"frame_start":1,"instance_id":5,"signer_id":20,"source":"handspeak","split":"val","url":"https:\/\/www.handspeak.com\/word\/b\/blood.mp4","variation_id":0,"video_id":"06735"},{"bbox":[61,9,216,192],"fps":25,"frame_end":-1,"frame_start":1,"instance_id":6,"signer_id":11,"source":"signingsavvy","split":"train","url":"https:\/\/www.signingsavvy.com\/signs\/mp4\/14\/14044.mp4","variation_id":0,"video_id":"06736"},{"bbox":[0,13,218,240],"fps":25,"frame_end":-1,"frame_start":1,"instance_id":7,"signer_id":24,"source":"aslpro","split":"test","url":"http:\/\/www.aslpro.com\/main\/b\/blood.swf","variation_id":0,"video_id":"06737"},{"bbox":[183,53,559,400],"fps":25,"frame_end":-1,"frame_start":1,"instance_id":8,"signer_id":12,"source":"aslsearch","split":"train","url":"http:\/\/www.aslsearch.com\/signs\/videos\/bleed.mp4","variation_id":0,"video_id":"06738"}]},{"gloss":"cochlear implant","instances":[{"bbox":[0,0,360,240],"fps":25,"frame_end":4193,"frame_start":4121,"instance_id":0,"signer_id":9,"source":"asl5200","split":"train","url":"https:\/\/www.youtube.com\/watch?v=PPmQd2zWdP0","variation_id":0,"video_id":"11497"},{"bbox":[33,4,223,180],"fps":25,"frame_end":-1,"frame_start":1,"instance_id":1,"signer_id":99,"source":"aslsignbank","split":"train","url":"https:\/\/aslsignbank.haskins.yale.edu\/dictionary\/protected_media\/glossvideo\/ASL\/CO\/COCHLEAR-IMPLANT-2271.mp4","variation_id":0,"video_id":"65373"},{"bbox":[88,18,236,240],"fps":25,"frame_end":-1,"frame_start":1,"instance_id":2,"signer_id":2,"source":"spreadthesign","split":"train","url":"https:\/\/media.spreadthesign.com\/video\/mp4\/13\/94088.mp4","variation_id":0,"video_id":"11498"},{"bbox":[690,123,1856,1075],"fps":25,"frame_end":-1,"frame_start":1,"instance_id":3,"signer_id":31,"source":"signschool","split":"train","url":"https:\/\/signstock.blob.core.windows.net\/signschool\/videos\/db_uploads\/SignSchool%20Cochlear%20Implant-4Qa3sWqLpIE.mp4","variation_id":0,"video_id":"11499"},{"bbox":[351,136,1471,1080],"fps":25,"frame_end":-1,"frame_start":1,"instance_id":4,"signer_id":45,"source":"signschool","split":"val","url":"https:\/\/signstock.blob.core.windows.net\/signschool\/videos\/db_uploads\/SignSchool%20Cochlear%20Implant-T9TdAOFFE2E.mp4","variation_id":0,"video_id":"11500"},{"bbox":[107,28,507,480],"fps":25,"frame_end":-1,"frame_start":1,"instance_id":5,"signer_id":59,"source":"asldeafined","split":"val","url":"https:\/\/media.asldeafined.com\/vocabulary\/1466899619.2638.mp4","variation_id":0,"video_id":"11501"},{"bbox":[162,16,504,360],"fps":25,"frame_end":-1,"frame_start":1,"instance_id":6,"signer_id":14,"source":"handspeak","split":"train","url":"https:\/\/www.handspeak.com\/word\/c\/cochlear-implant.mp4","variation_id":0,"video_id":"11502"},{"bbox":[52,12,210,192],"fps":25,"frame_end":-1,"frame_start":1,"instance_id":7,"signer_id":11,"source":"signingsavvy","split":"test","url":"https:\/\/www.signingsavvy.com\/signs\/mp4\/14\/14196.mp4","variation_id":0,"video_id":"11503"},{"bbox":[66,8,211,192],"fps":25,"frame_end":-1,"frame_start":1,"instance_id":8,"signer_id":11,"source":"signingsavvy","split":"train","url":"https:\/\/www.signingsavvy.com\/signs\/mp4\/5\/5830.mp4","variation_id":0,"video_id":"11504"}]},{"gloss":"pregnant","instances":[{"bbox":[0,0,360,240],"fps":25,"frame_end":4613,"frame_start":4574,"instance_id":0,"signer_id":9,"source":"asl5200","split":"train","url":"https:\/\/www.youtube.com\/watch?v=zHd4YEFzpwE","variation_id":0,"video_id":"44232"},{"bbox":[272,24,942,720],"fps":25,"frame_end":79,"frame_start":1,"instance_id":1,"signer_id":112,"source":"lillybauer","split":"train","url":"https:\/\/www.youtube.com\/watch?v=Crr5N3bs58g","variation_id":0,"video_id":"68388"},{"bbox":[209,52,566,400],"fps":25,"frame_end":-1,"frame_start":1,"instance_id":5,"signer_id":12,"source":"aslsearch","split":"train","url":"http:\/\/www.aslsearch.com\/signs\/videos\/pregnant.mp4","variation_id":0,"video_id":"44242"},{"bbox":[72,26,228,240],"fps":25,"frame_end":-1,"frame_start":1,"instance_id":6,"signer_id":2,"source":"spreadthesign","split":"train","url":"https:\/\/media.spreadthesign.com\/video\/mp4\/13\/93996.mp4","variation_id":0,"video_id":"44233"},{"bbox":[453,62,884,720],"fps":25,"frame_end":-1,"frame_start":1,"instance_id":7,"signer_id":38,"source":"startasl","split":"val","url":"https:\/\/s3-us-west-1.amazonaws.com\/files.startasl.com\/asldictionary\/pregnant.mp4","variation_id":0,"video_id":"44234"},{"bbox":[133,0,558,480],"fps":25,"frame_end":-1,"frame_start":1,"instance_id":8,"signer_id":13,"source":"asldeafined","split":"val","url":"https:\/\/media.asldeafined.com\/vocabulary\/1468755316.2468.mp4","variation_id":0,"video_id":"44235"},{"bbox":[55,0,460,480],"fps":25,"frame_end":-1,"frame_start":1,"instance_id":9,"signer_id":14,"source":"handspeak","split":"train","url":"https:\/\/www.handspeak.com\/word\/p\/pregnant.mp4","variation_id":0,"video_id":"44236"},{"bbox":[64,11,215,192],"fps":25,"frame_end":-1,"frame_start":1,"instance_id":10,"signer_id":11,"source":"signingsavvy","split":"test","url":"https:\/\/www.signingsavvy.com\/signs\/mp4\/8\/8678.mp4","variation_id":0,"video_id":"44237"},{"bbox":[347,42,939,720],"fps":25,"frame_end":-1,"frame_start":1,"instance_id":12,"signer_id":5,"source":"aslu","split":"train","url":"https:\/\/www.youtube.com\/watch?v=h5taRMjdtlA","variation_id":0,"video_id":"44239"}]},{"gloss":"bone","instances":[{"bbox":[0,0,360,240],"fps":25,"frame_end":3709,"frame_start":3660,"instance_id":0,"signer_id":9,"source":"asl5200","split":"val","url":"https:\/\/www.youtube.com\/watch?v=pDqITge_TGs","variation_id":0,"video_id":"07032"},{"bbox":[190,26,487,370],"fps":25,"frame_end":-1,"frame_start":1,"instance_id":1,"signer_id":90,"source":"aslsignbank","split":"test","url":"https:\/\/aslsignbank.haskins.yale.edu\/dictionary\/protected_media\/glossvideo\/ASL\/BO\/BONE-362.mp4","variation_id":0,"video_id":"65224"},{"bbox":[109,24,371,360],"fps":25,"frame_end":-1,"frame_start":1,"instance_id":2,"signer_id":109,"source":"asllex","split":"train","url":"https:\/\/youtu.be\/U8KcDY1_m-M","variation_id":0,"video_id":"67422"},{"bbox":[685,157,1394,1080],"fps":25,"frame_end":-1,"frame_start":1,"instance_id":3,"signer_id":31,"source":"signschool","split":"train","url":"https:\/\/signstock.blob.core.windows.net\/signschool\/videos\/db_uploads\/SignSchool%20Bone-v2omi2hoxN8.mp4","variation_id":0,"video_id":"07033"},{"bbox":[64,5,253,240],"fps":25,"frame_end":-1,"frame_start":1,"instance_id":5,"signer_id":14,"source":"handspeak","split":"train","url":"https:\/\/www.handspeak.com\/word\/b\/bone.mp4","variation_id":0,"video_id":"07035"},{"bbox":[71,15,201,192],"fps":25,"frame_end":-1,"frame_start":1,"instance_id":6,"signer_id":11,"source":"signingsavvy","split":"val","url":"https:\/\/www.signingsavvy.com\/signs\/mp4\/5\/5375.mp4","variation_id":0,"video_id":"07036"},{"bbox":[4,10,226,240],"fps":25,"frame_end":-1,"frame_start":1,"instance_id":7,"signer_id":30,"source":"aslpro","split":"train","url":"http:\/\/www.aslpro.com\/main\/b\/bone.swf","variation_id":0,"video_id":"07037"},{"bbox":[160,54,527,400],"fps":25,"frame_end":-1,"frame_start":1,"instance_id":8,"signer_id":12,"source":"aslsearch","split":"train","url":"http:\/\/www.aslsearch.com\/signs\/videos\/bone.mp4","variation_id":0,"video_id":"07038"}]},{"gloss":"depressed","instances":[{"bbox":[0,0,360,240],"fps":25,"frame_end":1724,"frame_start":1625,"instance_id":0,"signer_id":9,"source":"asl5200","split":"val","url":"https:\/\/www.youtube.com\/watch?v=ChIupJBcxjs","variation_id":0,"video_id":"15647"},{"bbox":[147,21,515,480],"fps":25,"frame_end":2096,"frame_start":1978,"instance_id":1,"signer_id":121,"source":"northtexas","split":"test","url":"https:\/\/www.youtube.com\/watch?v=lvqGMGFmuV4","variation_id":0,"video_id":"70111"},{"bbox":[162,13,492,370],"fps":25,"frame_end":-1,"frame_start":1,"instance_id":2,"signer_id":102,"source":"aslsignbank","split":"train","url":"https:\/\/aslsignbank.haskins.yale.edu\/dictionary\/protected_media\/glossvideo\/ASL\/DE\/DEPRESSED-1248.mp4","variation_id":0,"video_id":"65466"},{"bbox":[418,54,830,720],"fps":25,"frame_end":-1,"frame_start":1,"instance_id":3,"signer_id":38,"source":"startasl","split":"train","url":"https:\/\/s3-us-west-1.amazonaws.com\/files.startasl.com\/asldictionary\/depressed.mp4","variation_id":0,"video_id":"15648"},{"bbox":[590,131,1550,1070],"fps":25,"frame_end":-1,"frame_start":1,"instance_id":4,"signer_id":31,"source":"signschool","split":"train","url":"https:\/\/signstock.blob.core.windows.net\/signschool\/videos\/db_uploads\/SignSchool%20Devastated-9G7Jh2SJkb8.mp4","variation_id":0,"video_id":"15649"},{"bbox":[74,28,559,480],"fps":25,"frame_end":-1,"frame_start":1,"instance_id":5,"signer_id":59,"source":"asldeafined","split":"val","url":"https:\/\/media.asldeafined.com\/vocabulary\/1466908225.8103.mp4","variation_id":0,"video_id":"15650"},{"bbox":[82,27,267,240],"fps":25,"frame_end":-1,"frame_start":1,"instance_id":6,"signer_id":14,"source":"handspeak","split":"train","url":"https:\/\/www.handspeak.com\/word\/d\/depressed.mp4","variation_id":0,"video_id":"15651"},{"bbox":[66,9,226,192],"fps":25,"frame_end":-1,"frame_start":1,"instance_id":7,"signer_id":11,"source":"signingsavvy","split":"train","url":"https:\/\/www.signingsavvy.com\/signs\/mp4\/14\/14580.mp4","variation_id":0,"video_id":"15652"}]},{"gloss":"diabetes","instances":[{"bbox":[0,0,360,240],"fps":25,"frame_end":2352,"frame_start":2280,"instance_id":0,"signer_id":9,"source":"asl5200","split":"val","url":"https:\/\/www.youtube.com\/watch?v=ChIupJBcxjs","variation_id":0,"video_id":"16001"},{"bbox":[63,10,261,240],"fps":25,"frame_end":-1,"frame_start":1,"instance_id":1,"signer_id":2,"source":"spreadthesign","split":"test","url":"https:\/\/media.spreadthesign.com\/video\/mp4\/13\/158145.mp4","variation_id":0,"video_id":"16002"},{"bbox":[732,50,1609,1077],"fps":25,"frame_end":-1,"frame_start":1,"instance_id":3,"signer_id":4,"source":"signschool","split":"train","url":"https:\/\/signstock.blob.core.windows.net\/signschool\/videos\/db_uploads\/SignSchool%20Sugar%2C%20Diabetes-d65br6hli5M.mp4","variation_id":0,"video_id":"16004"},{"bbox":[134,31,521,480],"fps":25,"frame_end":-1,"frame_start":1,"instance_id":4,"signer_id":59,"source":"asldeafined","split":"train","url":"https:\/\/media.asldeafined.com\/vocabulary\/1466909328.2025.mp4","variation_id":0,"video_id":"16005"},{"bbox":[114,0,455,480],"fps":25,"frame_end":-1,"frame_start":1,"instance_id":5,"signer_id":20,"source":"handspeak","split":"train","url":"https:\/\/www.handspeak.com\/word\/d\/diabetes.mp4","variation_id":0,"video_id":"16006"},{"bbox":[77,11,216,192],"fps":25,"frame_end":-1,"frame_start":1,"instance_id":6,"signer_id":11,"source":"signingsavvy","split":"val","url":"https:\/\/www.signingsavvy.com\/signs\/mp4\/9\/9305.mp4","variation_id":0,"video_id":"16007"},{"bbox":[0,17,220,240],"fps":25,"frame_end":-1,"frame_start":1,"instance_id":7,"signer_id":30,"source":"aslpro","split":"train","url":"http:\/\/www.aslpro.com\/main\/d\/diabetes.swf","variation_id":0,"video_id":"16008"},{"bbox":[202,61,547,400],"fps":25,"frame_end":-1,"frame_start":1,"instance_id":8,"signer_id":12,"source":"aslsearch","split":"train","url":"http:\/\/www.aslsearch.com\/signs\/videos\/diabetes.mp4","variation_id":0,"video_id":"16009"}]},{"gloss":"infection","instances":[{"bbox":[0,0,360,240],"fps":25,"frame_end":949,"frame_start":887,"instance_id":0,"signer_id":9,"source":"asl5200","split":"val","url":"https:\/\/www.youtube.com\/watch?v=K1YuKDdDp_k","variation_id":0,"video_id":"29561"},{"bbox":[205,30,527,370],"fps":25,"frame_end":-1,"frame_start":1,"instance_id":1,"signer_id":96,"source":"aslsignbank","split":"test","url":"https:\/\/aslsignbank.haskins.yale.edu\/dictionary\/protected_media\/glossvideo\/ASL\/IN\/INFECTION-1734.mp4","variation_id":0,"video_id":"65938"},{"bbox":[74,43,234,240],"fps":25,"frame_end":-1,"frame_start":1,"instance_id":2,"signer_id":2,"source":"spreadthesign","split":"train","url":"https:\/\/media.spreadthesign.com\/video\/mp4\/13\/91792.mp4","variation_id":0,"video_id":"29562"},{"bbox":[466,57,1521,1070],"fps":25,"frame_end":-1,"frame_start":1,"instance_id":3,"signer_id":4,"source":"signschool","split":"train","url":"https:\/\/signstock.blob.core.windows.net\/signschool\/videos\/db_uploads\/SignSchool%20Insurance%2C%20Infection%202-LI0x4ob24uU.mp4","variation_id":0,"video_id":"29563"},{"bbox":[523,69,1537,1073],"fps":25,"frame_end":-1,"frame_start":1,"instance_id":4,"signer_id":4,"source":"signschool","split":"train","url":"https:\/\/signstock.blob.core.windows.net\/signschool\/videos\/db_uploads\/SignSchool%20Insurance%2C%20Infection-MTAgnBXKKM0.mp4","variation_id":0,"video_id":"29564"},{"bbox":[69,18,538,480],"fps":25,"frame_end":-1,"frame_start":1,"instance_id":5,"signer_id":21,"source":"asldeafined","split":"val","url":"https:\/\/media.asldeafined.com\/vocabulary\/1468666719.58.mp4","variation_id":0,"video_id":"29565"},{"bbox":[78,15,208,192],"fps":25,"frame_end":-1,"frame_start":1,"instance_id":6,"signer_id":10,"source":"signingsavvy","split":"train","url":"https:\/\/www.signingsavvy.com\/signs\/mp4\/24\/24145.mp4","variation_id":0,"video_id":"29566"},{"bbox":[347,38,940,720],"fps":25,"frame_end":-1,"frame_start":1,"instance_id":7,"signer_id":5,"source":"aslu","split":"train","url":"https:\/\/www.youtube.com\/watch?v=f9CKzrX8wiA","variation_id":0,"video_id":"29567"}]},{"gloss":"sore throat","instances":[{"bbox":[68,4,236,240],"fps":25,"frame_end":-1,"frame_start":1,"instance_id":0,"signer_id":2,"source":"spreadthesign","split":"val","url":"https:\/\/media.spreadthesign.com\/video\/mp4\/13\/116953.mp4","variation_id":0,"video_id":"53340"},{"bbox":[441,52,831,720],"fps":25,"frame_end":-1,"frame_start":1,"instance_id":1,"signer_id":38,"source":"startasl","split":"test","url":"https:\/\/s3-us-west-1.amazonaws.com\/files.startasl.com\/asldictionary\/sore-throat2.mp4","variation_id":0,"video_id":"53341"},{"bbox":[351,33,745,480],"fps":25,"frame_end":-1,"frame_start":1,"instance_id":3,"signer_id":60,"source":"signschool","split":"train","url":"https:\/\/signstock.blob.core.windows.net\/signschool\/videos\/db_uploads\/SignSchool%20Sore%20Throat-LL1fx8KoKi0.mp4","variation_id":0,"video_id":"53343"},{"bbox":[142,0,536,480],"fps":25,"frame_end":-1,"frame_start":1,"instance_id":4,"signer_id":13,"source":"asldeafined","split":"train","url":"https:\/\/media.asldeafined.com\/vocabulary\/1468776684.2185.mp4","variation_id":0,"video_id":"53344"},{"bbox":[200,71,500,480],"fps":25,"frame_end":-1,"frame_start":1,"instance_id":5,"signer_id":34,"source":"asldeafined","split":"train","url":"https:\/\/media.asldeafined.com\/vocabulary\/1546575110.61.mp4","variation_id":0,"video_id":"53345"},{"bbox":[83,14,253,240],"fps":25,"frame_end":-1,"frame_start":1,"instance_id":6,"signer_id":14,"source":"handspeak","split":"val","url":"https:\/\/www.handspeak.com\/word\/s\/sore-throat.mp4","variation_id":0,"video_id":"53346"},{"bbox":[70,14,211,192],"fps":25,"frame_end":-1,"frame_start":1,"instance_id":7,"signer_id":11,"source":"signingsavvy","split":"train","url":"https:\/\/www.signingsavvy.com\/signs\/mp4\/9\/9242.mp4","variation_id":0,"video_id":"53347"},{"bbox":[3,2,218,240],"fps":25,"frame_end":-1,"frame_start":1,"instance_id":8,"signer_id":84,"source":"aslpro","split":"train","url":"http:\/\/www.aslpro.com\/main\/s\/sore_throat.swf","variation_id":0,"video_id":"53348"}]},{"gloss":"heart attack","instances":[{"bbox":[0,0,360,240],"fps":25,"frame_end":1166,"frame_start":1114,"instance_id":0,"signer_id":9,"source":"asl5200","split":"test","url":"https:\/\/www.youtube.com\/watch?v=SiBub8VD5wo","variation_id":0,"video_id":"27017"},{"bbox":[72,43,248,240],"fps":25,"frame_end":-1,"frame_start":1,"instance_id":1,"signer_id":2,"source":"spreadthesign","split":"val","url":"https:\/\/media.spreadthesign.com\/video\/mp4\/13\/91778.mp4","variation_id":0,"video_id":"27018"},{"bbox":[692,55,1645,1080],"fps":25,"frame_end":-1,"frame_start":1,"instance_id":2,"signer_id":4,"source":"signschool","split":"train","url":"https:\/\/signstock.blob.core.windows.net\/signschool\/videos\/db_uploads\/SignSchool%20Heart%20Attack-qZZoeMc4vTU.mp4","variation_id":0,"video_id":"27019"},{"bbox":[88,9,545,480],"fps":25,"frame_end":-1,"frame_start":1,"instance_id":3,"signer_id":21,"source":"asldeafined","split":"train","url":"https:\/\/media.asldeafined.com\/vocabulary\/1468580472.2357.mp4","variation_id":0,"video_id":"27020"},{"bbox":[107,0,571,480],"fps":25,"frame_end":-1,"frame_start":1,"instance_id":4,"signer_id":20,"source":"handspeak","split":"train","url":"https:\/\/www.handspeak.com\/word\/h\/heart-attack.mp4","variation_id":0,"video_id":"27021"},{"bbox":[87,14,230,192],"fps":25,"frame_end":-1,"frame_start":1,"instance_id":5,"signer_id":10,"source":"signingsavvy","split":"train","url":"https:\/\/www.signingsavvy.com\/signs\/mp4\/23\/23790.mp4","variation_id":0,"video_id":"27022"},{"bbox":[190,58,564,400],"fps":25,"frame_end":-1,"frame_start":1,"instance_id":6,"signer_id":12,"source":"aslsearch","split":"train","url":"http:\/\/www.aslsearch.com\/signs\/videos\/heart-attack.mp4","variation_id":0,"video_id":"27023"}]}]